pyproc_worker/__init__.py
pyproc_worker/cli.py
pyproc_worker-0.1.0.dist-info/METADATA
pyproc_worker-0.1.0.dist-info/WHEEL
pyproc_worker-0.1.0.dist-info/entry_points.txt
pyproc_worker-0.1.0.dist-info/top_level.txt
pyproc_worker-0.1.0.dist-info/RECORD
