Metadata-Version: 2.4
Name: pyproc-worker
Version: 0.1.0
Summary: Python worker for pyproc - Call Python from Go without CGO
Author: YuminosukeSato
Project-URL: Homepage, https://github.com/YuminosukeSato/pyproc
Project-URL: Documentation, https://github.com/YuminosukeSato/pyproc#readme
Project-URL: Repository, https://github.com/YuminosukeSato/pyproc
Project-URL: Issues, https://github.com/YuminosukeSato/pyproc/issues
Keywords: pyproc,worker,go,python,ipc,rpc,unix-socket
Classifier: Development Status :: 4 - Beta
Classifier: Intended Audience :: Developers
Classifier: Topic :: Software Development :: Libraries :: Python Modules
Classifier: License :: OSI Approved :: Apache Software License
Classifier: Programming Language :: Python :: 3
Classifier: Programming Language :: Python :: 3.9
Classifier: Programming Language :: Python :: 3.10
Classifier: Programming Language :: Python :: 3.11
Classifier: Programming Language :: Python :: 3.12
Classifier: Operating System :: POSIX
Classifier: Operating System :: Unix
Classifier: Operating System :: MacOS
Requires-Python: <3.13,>=3.9
Provides-Extra: dev
Requires-Dist: pytest>=7.0; extra == "dev"
Requires-Dist: pytest-asyncio>=0.21; extra == "dev"
Requires-Dist: ruff>=0.1.0; extra == "dev"
Provides-Extra: examples
Requires-Dist: numpy>=1.26.0; extra == "examples"
Requires-Dist: pandas>=2.0.0; extra == "examples"
Requires-Dist: scikit-learn>=1.3.0; extra == "examples"
